verysimplemodules/__init__.py
verysimplemodules/add.py
verysimplemodules/subtract.py
verysimplemodules/extras/__init__.py
verysimplemodules/extras/multiply.py
verysimplemodules-0.0.1.dist-info/METADATA
verysimplemodules-0.0.1.dist-info/WHEEL
verysimplemodules-0.0.1.dist-info/top_level.txt
verysimplemodules-0.0.1.dist-info/RECORD
